{"Zapatron 4000":"Unpriced","Zed Codestone (TCG)":"Unpriced","Zeenana Split":"Unpriced","Zeenana Toffee Apple":"Unpriced","Zero Gravity Training Area":"Unpriced","Zo Junior Action Figure":"Unpriced","Zombie Aisha (TCG)":"Unpriced","Zombie Anubis":"Unpriced","Zombie Bartamus":"Unpriced","Zombie Beekadoodle":"Unpriced","Zombie Boween":"Unpriced","Zombie Calabat":"Unpriced","Zombie Flotsam (TCG)":"Unpriced","Zombie Gallion":"Unpriced","Zombie Ghostkerchief":"Unpriced","Zombie Gobbler":"Unpriced","Zombie Gypmu":"Unpriced","Zombie Hatchet":"Unpriced","Zombie Huggy":"Unpriced","Zombie Karren":"Unpriced","Zombie Kepru":"Unpriced","Zombie Mauket":"Unpriced","Zombie Moltenore":"Unpriced","Zombie Moltenore (TCG)":"Unpriced","Zombie Nedler":"Unpriced","Zombie Neucloop":"Unpriced","Zombie Noil":"Unpriced","Zombie Pandaphant":"Unpriced","Zombie Slorg":"Unpriced","Zombie Spardel":"Unpriced","Zombie Splyke":"Unpriced","Zombie Spyder":"Unpriced","Zombie Symol":"Unpriced","Zombie Tyrowbee":"Unpriced","Zombie Wherfy":"Unpriced","Zombify (TCG)":"Unpriced","Zomutt (TCG)":"Unpriced","Zorlix (TCG)":"Unpriced"}